shorthair/__init__.py
shorthair/json.py
shorthair/proxy.py
shorthair-0.1.2.dist-info/LICENSE
shorthair-0.1.2.dist-info/WHEEL
shorthair-0.1.2.dist-info/METADATA
shorthair-0.1.2.dist-info/RECORD
